<?xml version="1.0"?>
<opencv_storage>
<stage7>
  <maxWeakCount>11</maxWeakCount>
  <stageThreshold>-1.5206640958786011e+000</stageThreshold>
  <weakClassifiers>
    <_>
      <internalNodes>
        0 -1 8314 -206308373 -405814803 -653240431 -2113127 -1223963973
        1191940224 -208997389 -671116289</internalNodes>
      <leafValues>
        -7.2093021869659424e-001 2.4743725080043077e-003</leafValues></_>
    <_>
      <internalNodes>
        0 -1 4361 1441788415 1470363599 -7645750 -605035637 -741674757
        1375715115 -219054614 -74449494</internalNodes>
      <leafValues>
        -4.1757726669311523e-001 3.4973496198654175e-001</leafValues></_>
    <_>
      <internalNodes>
        0 -1 5317 -1345395450 -2004446710 -787361420 -95006518
        1774410351 193700011 -510922400 -21546</internalNodes>
      <leafValues>
        -5.0542783737182617e-001 2.5893995165824890e-001</leafValues></_>
    <_>
      <internalNodes>
        0 -1 1791 676340432 -7294859 -1714047745 -35847288 -339886083
        -549508165 1033711037 -1476129536</internalNodes>
      <leafValues>
        -5.0278449058532715e-001 2.6722767949104309e-001</leafValues></_>
    <_>
      <internalNodes>
        0 -1 1187 -714607450 -683276918 -1470898482 -150061176 282330495
        1502461838 1088396780 1781518091</internalNodes>
      <leafValues>
        -4.5713004469871521e-001 2.8918460011482239e-001</leafValues></_>
    <_>
      <internalNodes>
        0 -1 6488 -114361347 -1611464708 -73588996 -1073746952 939357693
        1040014846 -2046874116 -536936999</internalNodes>
      <leafValues>
        -3.1110826134681702e-001 4.0420189499855042e-001</leafValues></_>
    <_>
      <internalNodes>
        0 -1 6385 -1416109278 -1518190390 -1053798382 -190969020
        -1985254933 -895827832 1436086773 -441715980</internalNodes>
      <leafValues>
        -4.8148316144943237e-001 2.6440948247909546e-001</leafValues></_>
    <_>
      <internalNodes>
        0 -1 135 -28127370 -2702705 -117242881 -808309913 38813181
        -70200693 -1154670257 1643332679</internalNodes>
      <leafValues>
        -4.1959014534950256e-001 3.2589784264564514e-001</leafValues></_>
    <_>
      <internalNodes>
        0 -1 7119 982786021 -19213485 -956186145 -1194426149 -610538501
        -376799224 -1148639041 -1091030212</internalNodes>
      <leafValues>
        -5.0360316038131714e-001 2.5914174318313599e-001</leafValues></_>
    <_>
      <internalNodes>
        0 -1 6377 -439357525 -808467064 -1255948462 -710938237
        -1013974729 -905016485 -196384777 -984123917</internalNodes>
      <leafValues>
        -4.1712924838066101e-001 3.0912807583808899e-001</leafValues></_>
    <_>
      <internalNodes>
        0 -1 4051 187106231 439107794 -1872656929 -1164312293 296244824
        -16170837 -73344520 -1906830536</internalNodes>
      <leafValues>
        -5.0616282224655151e-001 2.6241067051887512e-001</leafValues></_></weakClassifiers></stage7>
</opencv_storage>
